{
  "lastUpdated": "07/12/25",
  "treasuryValue": 373682,
  "treasuryGen1": 336313,
  "treasuryGen2": 37368,
  "solPrice": 133,
  "nftGen1Value": 673,
  "nftGen1ValueSol": "5.05",
  "nftGen2Value": 42,
  "nftGen2ValueSol": "0.32",
  "gen1ListingPrice": 283,
  "gen1ListingPriceSol": "2.12",
  "gen2ListingPrice": 43,
  "gen2ListingPriceSol": "0.33",
  "gen1Discount": "-58.00",
  "gen1DiscountLabel": "In sconto",
  "gen2Discount": "3.13",
  "gen2DiscountLabel": "Sopravvalutato",
  "stableValue": 181788,
  "stablePercentage": 49
}