{
  "lastUpdated": "06/06/25",
  "treasuryValue": 487098,
  "treasuryGen1": 438388,
  "treasuryGen2": 48710,
  "solPrice": 147,
  "nftGen1Value": 877,
  "nftGen1ValueSol": "5.97",
  "nftGen2Value": 55,
  "nftGen2ValueSol": "0.37",
  "gen1ListingPrice": 623,
  "gen1ListingPriceSol": "4.24",
  "gen2ListingPrice": 78,
  "gen2ListingPriceSol": "0.53",
  "gen1Discount": "-28.93",
  "gen1DiscountLabel": "In sconto",
  "gen2Discount": "41.71",
  "gen2DiscountLabel": "Sopravvalutato",
  "stableValue": 177357,
  "stablePercentage": 36
}