{
  "lastUpdated": "27/10/25",
  "treasuryValue": 481502,
  "treasuryGen1": 433352,
  "treasuryGen2": 48150,
  "solPrice": 204,
  "nftGen1Value": 867,
  "nftGen1ValueSol": "4.26",
  "nftGen2Value": 54,
  "nftGen2ValueSol": "0.27",
  "gen1ListingPrice": 800,
  "gen1ListingPriceSol": "3.93",
  "gen2ListingPrice": 52,
  "gen2ListingPriceSol": "0.26",
  "gen1Discount": "-7.64",
  "gen1DiscountLabel": "In sconto",
  "gen2Discount": "-3.55",
  "gen2DiscountLabel": "In sconto",
  "stableValue": 175929,
  "stablePercentage": 37
}