{
  "lastUpdated": "01/06/25",
  "treasuryValue": 421267,
  "treasuryGen1": 379140,
  "treasuryGen2": 42127,
  "solPrice": 155,
  "nftGen1Value": 758,
  "nftGen1ValueSol": "4.89",
  "nftGen2Value": 47,
  "nftGen2ValueSol": "0.31",
  "gen1ListingPrice": 518,
  "gen1ListingPriceSol": "3.34",
  "gen2ListingPrice": 82,
  "gen2ListingPriceSol": "0.53",
  "gen1Discount": "-31.71",
  "gen1DiscountLabel": "In sconto",
  "gen2Discount": "73.26",
  "gen2DiscountLabel": "Sopravvalutato",
  "stableValue": 178234,
  "stablePercentage": 42
}