{
  "lastUpdated": "15/05/26",
  "updatedAt": "2026-05-15T06:48:14.813Z",
  "wallet": "EKjb5grMX19c3cAZa5LQjqksDpqqVLTGZrswh79WkPdD",
  "totalValue": 376541.792823245,
  "stableValue": 146504.20372485914,
  "nonStableValue": 230037.58909838586,
  "tokens": [
    {
      "name": "Ondo US Dollar Yield",
      "symbol": "USDY",
      "amount": 128153.246163,
      "price": 1.1313510475304,
      "value": 144986.30929093127,
      "mint": "A1KLoBrKBde8Ty9qtNQUtq3C2ortoC3u7twggz7sEto6",
      "decimals": 6,
      "isStable": true
    },
    {
      "name": "Bella Bumper Play 2 Earn",
      "symbol": "PISTA",
      "amount": 42500000,
      "price": 0.002151197580153231,
      "value": 91425.89715651232,
      "mint": "9CaQUthsVMugZzMvskrrvcHXyjFqHGdNtGkPT8QSRACE",
      "decimals": 8,
      "isStable": false
    },
    {
      "name": "Jito Staked SOL",
      "symbol": "JitoSOL",
      "amount": 467.814865345,
      "price": 116.32335967698793,
      "value": 54417.79684376811,
      "mint": "J1toso1uCk3RLmjorhTtrVwY9HJ7X8V9yYac6Y7kGCPn",
      "decimals": 9,
      "isStable": false
    },
    {
      "name": "tBTC v2",
      "symbol": "tBTC",
      "amount": 0.50078587,
      "price": 80243.6305238578,
      "value": 40184.876323848686,
      "mint": "6DNSN2BJsaPFdFFc1zP37kkeNe4Usc1Sqkzr9C9vPWcU",
      "decimals": 8,
      "isStable": false
    },
    {
      "name": "Zcash",
      "symbol": "ZEC",
      "amount": 30.54596389,
      "price": 544.9432817162551,
      "value": 16645.817805402825,
      "mint": "A7bdiYdS5GjqGFtxf17ppRHtDKPkkRqbKtR27dxvQXaS",
      "decimals": 8,
      "isStable": false
    },
    {
      "name": "Solana",
      "symbol": "SOL",
      "amount": 116.393216868,
      "price": 91.03009734521414,
      "value": 10595.285861816661,
      "mint": "SOL",
      "decimals": 9,
      "isStable": false
    },
    {
      "name": "Nummus Aeternitas",
      "symbol": "NUMMUS",
      "amount": 1169190.021629,
      "price": 0.008312094787009769,
      "value": 9718.41828380625,
      "mint": "9JK2U7aEkp3tWaFNuaJowWRgNys5DVaKGxWk73VT5ray",
      "decimals": 6,
      "isStable": false
    },
    {
      "name": "Jupiter",
      "symbol": "JUP",
      "amount": 27013.923334,
      "price": 0.2181546314957489,
      "value": 5893.212490183182,
      "mint": "JUPyiwrYJFskUPiHa7hkeR8VUtAeFoSYbKedZNsDvCN",
      "decimals": 6,
      "isStable": false
    },
    {
      "name": "USD Coin",
      "symbol": "USDC",
      "amount": 1518.303167,
      "price": 0.9997307961407029,
      "value": 1517.8944339278607,
      "mint": "EPjFWdd5AufqSSqeM2qN1xzybapC8G4wEGGkZwyTDt1v",
      "decimals": 6,
      "isStable": true
    },
    {
      "name": "Punchy Puff",
      "symbol": "PUNCHY",
      "amount": 7354733.555938,
      "price": 0.00007392460873809623,
      "value": 543.6958004956639,
      "mint": "GnYufMbTAMz1DzkSN2DmwkBzjMTLkM22WvQuN1VCbonk",
      "decimals": 6,
      "isStable": false
    },
    {
      "name": "Kamino",
      "symbol": "KMNO",
      "amount": 17623.716087,
      "price": 0.022211697384079694,
      "value": 391.4526485073811,
      "mint": "KMNo3nJsBXfcpJTVhZcXLW7RmTwTt4GVFE7suUBo9sS",
      "decimals": 6,
      "isStable": false
    },
    {
      "name": "Threshold Network Tok (Wormhole)",
      "symbol": "T",
      "amount": 29151.44467348,
      "price": 0.005985782520073517,
      "value": 174.4942079614068,
      "mint": "4Njvi3928U3figEF5tf8xvjLC5GqUN33oe4XTJNe7xXC",
      "decimals": 8,
      "isStable": false
    },
    {
      "name": "Pudgy Penguins",
      "symbol": "PENGU",
      "amount": 3490.000266,
      "price": 0.00902252498988468,
      "value": 31.48861461468918,
      "mint": "2zMMhcVQEXDtdE6vsFS7S7D5oUodfJHE8vd1gnBouauv",
      "decimals": 6,
      "isStable": false
    },
    {
      "name": "Only1 (LIKE)",
      "symbol": "LIKE",
      "amount": 7456.128850154,
      "price": 0.0013419370525677241,
      "value": 10.005655572740833,
      "mint": "3bRTivrVsitbmCTGtqwp7hxXPsybkjn4XLNtPsHqa3zR",
      "decimals": 9,
      "isStable": false
    },
    {
      "name": "SynesisOne",
      "symbol": "SNS",
      "amount": 77779.580536727,
      "price": 0.000060382058579375595,
      "value": 4.6964911882479115,
      "mint": "SNSNkV9zfG5ZKWQs6x4hxvBRV6s8SqMfSGCtECDvdMd",
      "decimals": 9,
      "isStable": false
    },
    {
      "name": "Yes Token",
      "symbol": "YES",
      "amount": 11607.538101999,
      "price": 0.000010464552623600606,
      "value": 0.12146769329881764,
      "mint": "32h846XXTSWGUaaKHMC5b2e39n1nwJD6UtDBppX5p4E9",
      "decimals": 9,
      "isStable": false
    },
    {
      "name": "WIMDY 2.0",
      "symbol": "WIMDY 2.0",
      "amount": 1300000,
      "price": 5.2852747667587005e-8,
      "value": 0.0687085719678631,
      "mint": "EETgMghWtwKnkkwZMvcG5fVW6MjmxRqphJjKi4xcfXUj",
      "decimals": 6,
      "isStable": false
    },
    {
      "name": "IO",
      "symbol": "IO",
      "amount": 0.46857397,
      "price": 0.14271599977325222,
      "value": 0.0668730025962719,
      "mint": "BZLbGTNCSFfoth2GYDtwr7e4imWzpR5jqcUuGEwr646K",
      "decimals": 8,
      "isStable": false
    },
    {
      "name": "SolCex ",
      "symbol": "SOLCEX",
      "amount": 24.4434,
      "price": 0.0019120505210311837,
      "value": 0.046737015705773634,
      "mint": "AMjzRn1TBQwQfNAjHFeBb7uGbbqbJB7FzXAnGgdFPk6K",
      "decimals": 6,
      "isStable": false
    },
    {
      "name": "Pyth Network",
      "symbol": "PYTH",
      "amount": 0.893082,
      "price": 0.04893099415182218,
      "value": 0.04369939011909766,
      "mint": "HZ1JovNiVvGrGNiiYvEozEVgZ58xaU3RKwX8eACQBCt3",
      "decimals": 6,
      "isStable": false
    },
    {
      "name": "STEAK",
      "symbol": "STEAK",
      "amount": 103639.665,
      "price": 3.109773132987378e-7,
      "value": 0.03222958457288123,
      "mint": "STEAK3frqdoKybo3R8LU85BcfajYd7dVEHiYVBcD3rG",
      "decimals": 5,
      "isStable": false
    },
    {
      "name": "Lamas Finance",
      "symbol": "LMF",
      "amount": 13,
      "price": 0.0024130402502686213,
      "value": 0.03136952325349208,
      "mint": "LMFzmYL6y1FX8HsEmZ6yNKNzercBmtmpg2ZoLwuUboU",
      "decimals": 9,
      "isStable": false
    },
    {
      "name": "Lorm The Worm",
      "symbol": "L",
      "amount": 3188.7,
      "price": 0.000007965272899574535,
      "value": 0.025398865694873318,
      "mint": "2emYMetySwE7Xh6qrG1AwAQ3TDvrLkUSpSZ5AjcWCc7B",
      "decimals": 6,
      "isStable": false
    },
    {
      "name": "Parcl",
      "symbol": "PRCL",
      "amount": 0.758439,
      "price": 0.013653647304398202,
      "value": 0.010355458607900467,
      "mint": "4LLbsb5ReP3yEtYzmXewyGjcir5uXtKFURtaEUVC2AHs",
      "decimals": 6,
      "isStable": false
    },
    {
      "name": "Buttercat",
      "symbol": "BUTT",
      "amount": 300,
      "price": 0.000008101131178931296,
      "value": 0.002430339353679389,
      "mint": "3dCCbYca3jSgRdDiMEeV5e3YKNzsZAp3ZVfzUsbb4be4",
      "decimals": 6,
      "isStable": false
    },
    {
      "name": "Solmedia",
      "symbol": "MEDIA",
      "amount": 10,
      "price": 0.00011806743793991134,
      "value": 0.0011806743793991133,
      "mint": "BNT4uhSStq1beFADv3cq4wQAVfWB392PjAaxTBpNeWxu",
      "decimals": 6,
      "isStable": false
    },
    {
      "name": "cat in a dogs world",
      "symbol": "MEW",
      "amount": 0.69285,
      "price": 0.0006060087947704023,
      "value": 0.0004198731934566732,
      "mint": "MEW1gQWJ3nEXg2qgERiKu7FAFj79PHvQVREQUzScPP5",
      "decimals": 5,
      "isStable": false
    },
    {
      "name": "Wormhole Token",
      "symbol": "W",
      "amount": 0.00317,
      "price": 0.01393334302343558,
      "value": 0.00004416869738429079,
      "mint": "85VBFQZC9TZkfaptBWjvUw7YbZjy52A6mjtPGjstQAmQ",
      "decimals": 6,
      "isStable": false
    },
    {
      "name": "Wen",
      "symbol": "WEN",
      "amount": 0.08034,
      "price": 0.00000679916603578986,
      "value": 5.462449993153573e-7,
      "mint": "WENWENvqqNya429ubCdR81ZmD69brwQaaBYY6p3LCpk",
      "decimals": 5,
      "isStable": false
    }
  ]
}